rainpy/__init__.py
rainpy/__main__.py
rainpy/core.py
rainpy/raindrop.py
rainpy/read.py
rainpy/run.py
rainpy/save.py
rainpy/test_instances.py
rainpy/utils.py
rainpy-0.13.0.dist-info/licenses/LICENSE
rainpy-0.13.0.dist-info/METADATA
rainpy-0.13.0.dist-info/WHEEL
rainpy-0.13.0.dist-info/top_level.txt
rainpy-0.13.0.dist-info/RECORD
