Metadata-Version: 2.4
Name: rainpy
Version: 0.13.0
Summary: Add your description here
Requires-Python: >=3.8
License-File: LICENSE
Requires-Dist: chardet>=5.2.0
Requires-Dist: diskcache>=5.6.3
Requires-Dist: jsonlines>=4.0.0
Requires-Dist: pandas>=2.3.3
Requires-Dist: pytest>=8.4.2
Dynamic: license-file
